django_stats_middleware/__init__.py
django_stats_middleware/apps.py
django_stats_middleware-0.3.dist-info/LICENSE.md
django_stats_middleware-0.3.dist-info/METADATA
django_stats_middleware-0.3.dist-info/WHEEL
django_stats_middleware-0.3.dist-info/top_level.txt
django_stats_middleware-0.3.dist-info/RECORD
